printk/__init__.py
printk/printk.py
printcolorful-0.2.6.dist-info/METADATA
printcolorful-0.2.6.dist-info/WHEEL
printcolorful-0.2.6.dist-info/top_level.txt
printcolorful-0.2.6.dist-info/RECORD
